{"fileName":"2-4","name":"可可岛（夜） ★☆","background":"本关为限定卡组作战\r\n新增卡片“樱桃反弹布丁”，它能够反弹射手与投手的弹体，尤其是和“双向水管”结合时，会有出乎意料的效果？！\r\n","illustrate":"夜间3行陆地+4行水域\r\n本关初始没有猫猫保护\r\n推荐先将人物使用武器更换为“双向水枪”\r\n","additionalNotes":"将布丁放置在左1列，就能反弹水管的子弹了，然后老鼠就会：啊啊啊啊啊啊啊啊啊啊啊\r\n","chapterIndex":0,"sceneIndex":10,"stageIndex":0,"startCost":125,"isEnableTimeLimit":false,"totalSeconds":0,"isEnableCardLimit":true,"availableCardInfoList":[{"type":1,"maxShape":0,"maxLevel":5},{"type":4,"maxShape":0,"maxLevel":5},{"type":6,"maxShape":0,"maxLevel":5},{"type":9,"maxShape":0,"maxLevel":5}],"isEnableCardCount":true,"cardCount":4,"isEnableJewelCount":true,"jewelCount":0,"pauseCount":-1,"difficulty":0,"roundInfoList":[{"name":"第1轮","info":"","roundInfoList":[{"name":"第1轮","info":"","roundInfoList":[],"baseEnemyGroupList":[{"mApartIndex":0,"mStartIndex":0,"mEnemyInfo":{"type":0,"shape":3},"mCount":1,"mHp":0.0,"mEnemyAttribute":{"HpRate":1.0,"AttackRate":1.0,"MoveSpeedRate":1.0,"Defence":0.0,"ParamDict":{}}}],"interval":0,"endTime":720,"roundMode":1,"isShowBigWaveRound":false,"isBossRound":false,"isSkipWhenBossDie":false,"bossList":null,"musicRefenceName":null,"ParamArrayDict":{}},{"name":"第2轮","info":"","roundInfoList":[],"baseEnemyGroupList":[{"mApartIndex":0,"mStartIndex":0,"mEnemyInfo":{"type":0,"shape":3},"mCount":2,"mHp":0.0,"mEnemyAttribute":{"HpRate":1.0,"AttackRate":1.0,"MoveSpeedRate":1.0,"Defence":0.0,"ParamDict":{}}}],"interval":0,"endTime":720,"roundMode":1,"isShowBigWaveRound":false,"isBossRound":false,"isSkipWhenBossDie":false,"bossList":null,"musicRefenceName":null,"ParamArrayDict":{}},{"name":"第3轮","info":"","roundInfoList":[],"baseEnemyGroupList":[{"mApartIndex":0,"mStartIndex":0,"mEnemyInfo":{"type":0,"shape":1},"mCount":3,"mHp":0.0,"mEnemyAttribute":{"HpRate":1.0,"AttackRate":1.0,"MoveSpeedRate":1.0,"Defence":0.0,"ParamDict":{}}}],"interval":0,"endTime":720,"roundMode":1,"isShowBigWaveRound":false,"isBossRound":false,"isSkipWhenBossDie":false,"bossList":null,"musicRefenceName":null,"ParamArrayDict":{}},{"name":"第4轮","info":"","roundInfoList":[],"baseEnemyGroupList":[{"mApartIndex":2,"mStartIndex":0,"mEnemyInfo":{"type":0,"shape":2},"mCount":2,"mHp":0.0,"mEnemyAttribute":{"HpRate":1.0,"AttackRate":1.0,"MoveSpeedRate":1.0,"Defence":0.0,"ParamDict":{}}}],"interval":0,"endTime":720,"roundMode":1,"isShowBigWaveRound":false,"isBossRound":false,"isSkipWhenBossDie":false,"bossList":null,"musicRefenceName":null,"ParamArrayDict":{}},{"name":"第5轮","info":"","roundInfoList":[],"baseEnemyGroupList":[{"mApartIndex":0,"mStartIndex":0,"mEnemyInfo":{"type":6,"shape":0},"mCount":2,"mHp":0.0,"mEnemyAttribute":{"HpRate":1.0,"AttackRate":1.0,"MoveSpeedRate":1.0,"Defence":0.0,"ParamDict":{}}},{"mApartIndex":0,"mStartIndex":0,"mEnemyInfo":{"type":0,"shape":1},"mCount":2,"mHp":0.0,"mEnemyAttribute":{"HpRate":1.0,"AttackRate":1.0,"MoveSpeedRate":1.0,"Defence":0.0,"ParamDict":{}}},{"mApartIndex":1,"mStartIndex":0,"mEnemyInfo":{"type":0,"shape":3},"mCount":2,"mHp":0.0,"mEnemyAttribute":{"HpRate":1.0,"AttackRate":1.0,"MoveSpeedRate":1.0,"Defence":0.0,"ParamDict":{}}}],"interval":2,"endTime":714,"roundMode":1,"isShowBigWaveRound":false,"isBossRound":false,"isSkipWhenBossDie":false,"bossList":null,"musicRefenceName":null,"ParamArrayDict":{}},{"name":"第6轮","info":"","roundInfoList":[{"name":"第1轮","info":"","roundInfoList":[],"baseEnemyGroupList":[{"mApartIndex":1,"mStartIndex":0,"mEnemyInfo":{"type":0,"shape":2},"mCount":2,"mHp":0.0,"mEnemyAttribute":{"HpRate":1.0,"AttackRate":1.0,"MoveSpeedRate":1.0,"Defence":0.0,"ParamDict":{}}}],"interval":0,"endTime":120,"roundMode":0,"isShowBigWaveRound":false,"isBossRound":false,"isSkipWhenBossDie":false,"bossList":null,"musicRefenceName":null,"ParamArrayDict":{}},{"name":"第2轮","info":"","roundInfoList":[],"baseEnemyGroupList":[{"mApartIndex":0,"mStartIndex":2,"mEnemyInfo":{"type":0,"shape":0},"mCount":4,"mHp":0.0,"mEnemyAttribute":{"HpRate":1.0,"AttackRate":1.0,"MoveSpeedRate":1.0,"Defence":0.0,"ParamDict":{}}},{"mApartIndex":1,"mStartIndex":0,"mEnemyInfo":{"type":11,"shape":0},"mCount":2,"mHp":0.0,"mEnemyAttribute":{"HpRate":1.0,"AttackRate":1.0,"MoveSpeedRate":1.0,"Defence":0.0,"ParamDict":{}}}],"interval":2,"endTime":596,"roundMode":0,"isShowBigWaveRound":false,"isBossRound":false,"isSkipWhenBossDie":false,"bossList":null,"musicRefenceName":null,"ParamArrayDict":{}}],"baseEnemyGroupList":[],"interval":0,"endTime":0,"roundMode":1,"isShowBigWaveRound":false,"isBossRound":false,"isSkipWhenBossDie":false,"bossList":null,"musicRefenceName":null,"ParamArrayDict":{}},{"name":"第7轮","info":"","roundInfoList":[{"name":"第1轮","info":"","roundInfoList":[],"baseEnemyGroupList":[{"mApartIndex":0,"mStartIndex":0,"mEnemyInfo":{"type":0,"shape":1},"mCount":2,"mHp":0.0,"mEnemyAttribute":{"HpRate":1.0,"AttackRate":1.0,"MoveSpeedRate":1.0,"Defence":0.0,"ParamDict":{}}},{"mApartIndex":0,"mStartIndex":2,"mEnemyInfo":{"type":0,"shape":3},"mCount":1,"mHp":0.0,"mEnemyAttribute":{"HpRate":1.0,"AttackRate":1.0,"MoveSpeedRate":1.0,"Defence":0.0,"ParamDict":{}}},{"mApartIndex":0,"mStartIndex":0,"mEnemyInfo":{"type":0,"shape":0},"mCount":3,"mHp":0.0,"mEnemyAttribute":{"HpRate":1.0,"AttackRate":1.0,"MoveSpeedRate":1.0,"Defence":0.0,"ParamDict":{}}}],"interval":2,"endTime":114,"roundMode":0,"isShowBigWaveRound":false,"isBossRound":false,"isSkipWhenBossDie":false,"bossList":null,"musicRefenceName":null,"ParamArrayDict":{}},{"name":"第2轮","info":"","roundInfoList":[],"baseEnemyGroupList":[{"mApartIndex":1,"mStartIndex":0,"mEnemyInfo":{"type":6,"shape":0},"mCount":2,"mHp":0.0,"mEnemyAttribute":{"HpRate":1.0,"AttackRate":1.0,"MoveSpeedRate":1.0,"Defence":0.0,"ParamDict":{}}}],"interval":0,"endTime":600,"roundMode":0,"isShowBigWaveRound":false,"isBossRound":false,"isSkipWhenBossDie":false,"bossList":null,"musicRefenceName":null,"ParamArrayDict":{}}],"baseEnemyGroupList":[],"interval":0,"endTime":0,"roundMode":1,"isShowBigWaveRound":false,"isBossRound":false,"isSkipWhenBossDie":false,"bossList":null,"musicRefenceName":null,"ParamArrayDict":{}},{"name":"第8轮","info":"","roundInfoList":[{"name":"第1轮","info":"","roundInfoList":[],"baseEnemyGroupList":[{"mApartIndex":0,"mStartIndex":0,"mEnemyInfo":{"type":0,"shape":2},"mCount":2,"mHp":0.0,"mEnemyAttribute":{"HpRate":1.0,"AttackRate":1.0,"MoveSpeedRate":1.0,"Defence":0.0,"ParamDict":{}}},{"mApartIndex":1,"mStartIndex":0,"mEnemyInfo":{"type":11,"shape":1},"mCount":2,"mHp":0.0,"mEnemyAttribute":{"HpRate":1.0,"AttackRate":1.0,"MoveSpeedRate":1.0,"Defence":0.0,"ParamDict":{}}},{"mApartIndex":1,"mStartIndex":2,"mEnemyInfo":{"type":14,"shape":0},"mCount":2,"mHp":0.0,"mEnemyAttribute":{"HpRate":1.0,"AttackRate":1.0,"MoveSpeedRate":1.0,"Defence":0.0,"ParamDict":{}}}],"interval":2,"endTime":114,"roundMode":0,"isShowBigWaveRound":false,"isBossRound":false,"isSkipWhenBossDie":false,"bossList":null,"musicRefenceName":null,"ParamArrayDict":{}},{"name":"第2轮","info":"","roundInfoList":[],"baseEnemyGroupList":[{"mApartIndex":0,"mStartIndex":2,"mEnemyInfo":{"type":0,"shape":3},"mCount":4,"mHp":0.0,"mEnemyAttribute":{"HpRate":1.0,"AttackRate":1.0,"MoveSpeedRate":1.0,"Defence":0.0,"ParamDict":{}}},{"mApartIndex":1,"mStartIndex":0,"mEnemyInfo":{"type":0,"shape":1},"mCount":2,"mHp":0.0,"mEnemyAttribute":{"HpRate":1.0,"AttackRate":1.0,"MoveSpeedRate":1.0,"Defence":0.0,"ParamDict":{}}},{"mApartIndex":1,"mStartIndex":2,"mEnemyInfo":{"type":0,"shape":3},"mCount":2,"mHp":0.0,"mEnemyAttribute":{"HpRate":1.0,"AttackRate":1.0,"MoveSpeedRate":1.0,"Defence":0.0,"ParamDict":{}}}],"interval":2,"endTime":594,"roundMode":0,"isShowBigWaveRound":false,"isBossRound":false,"isSkipWhenBossDie":false,"bossList":null,"musicRefenceName":null,"ParamArrayDict":{}}],"baseEnemyGroupList":[],"interval":0,"endTime":0,"roundMode":1,"isShowBigWaveRound":true,"isBossRound":false,"isSkipWhenBossDie":false,"bossList":null,"musicRefenceName":null,"ParamArrayDict":{}}],"baseEnemyGroupList":[],"interval":0,"endTime":0,"roundMode":1,"isShowBigWaveRound":false,"isBossRound":false,"isSkipWhenBossDie":false,"bossList":null,"musicRefenceName":null,"ParamArrayDict":{}},{"name":"第4轮","info":"","roundInfoList":[{"name":"第1轮","info":"","roundInfoList":[{"name":"第1轮","info":"","roundInfoList":[],"baseEnemyGroupList":[{"mApartIndex":0,"mStartIndex":0,"mEnemyInfo":{"type":1,"shape":0},"mCount":2,"mHp":0.0,"mEnemyAttribute":{"HpRate":1.0,"AttackRate":1.0,"MoveSpeedRate":1.0,"Defence":0.0,"ParamDict":{}}},{"mApartIndex":0,"mStartIndex":3,"mEnemyInfo":{"type":0,"shape":4},"mCount":2,"mHp":0.0,"mEnemyAttribute":{"HpRate":1.0,"AttackRate":1.0,"MoveSpeedRate":1.0,"Defence":0.0,"ParamDict":{}}},{"mApartIndex":1,"mStartIndex":0,"mEnemyInfo":{"type":11,"shape":1},"mCount":5,"mHp":0.0,"mEnemyAttribute":{"HpRate":1.0,"AttackRate":1.0,"MoveSpeedRate":1.0,"Defence":0.0,"ParamDict":{}}}],"interval":2,"endTime":112,"roundMode":0,"isShowBigWaveRound":false,"isBossRound":false,"isSkipWhenBossDie":false,"bossList":null,"musicRefenceName":null,"ParamArrayDict":{}},{"name":"第2轮","info":"","roundInfoList":[],"baseEnemyGroupList":[{"mApartIndex":0,"mStartIndex":0,"mEnemyInfo":{"type":0,"shape":1},"mCount":6,"mHp":0.0,"mEnemyAttribute":{"HpRate":1.0,"AttackRate":1.0,"MoveSpeedRate":1.0,"Defence":0.0,"ParamDict":{}}}],"interval":2,"endTime":596,"roundMode":0,"isShowBigWaveRound":false,"isBossRound":false,"isSkipWhenBossDie":false,"bossList":null,"musicRefenceName":null,"ParamArrayDict":{}}],"baseEnemyGroupList":[],"interval":0,"endTime":0,"roundMode":1,"isShowBigWaveRound":false,"isBossRound":false,"isSkipWhenBossDie":false,"bossList":null,"musicRefenceName":null,"ParamArrayDict":{}},{"name":"第2轮","info":"","roundInfoList":[{"name":"第1轮","info":"","roundInfoList":[],"baseEnemyGroupList":[{"mApartIndex":0,"mStartIndex":0,"mEnemyInfo":{"type":6,"shape":0},"mCount":2,"mHp":0.0,"mEnemyAttribute":{"HpRate":1.0,"AttackRate":1.0,"MoveSpeedRate":1.0,"Defence":0.0,"ParamDict":{}}},{"mApartIndex":1,"mStartIndex":0,"mEnemyInfo":{"type":14,"shape":0},"mCount":4,"mHp":0.0,"mEnemyAttribute":{"HpRate":1.0,"AttackRate":1.0,"MoveSpeedRate":1.0,"Defence":0.0,"ParamDict":{}}}],"interval":2,"endTime":116,"roundMode":0,"isShowBigWaveRound":false,"isBossRound":false,"isSkipWhenBossDie":false,"bossList":null,"musicRefenceName":null,"ParamArrayDict":{}},{"name":"第2轮","info":"","roundInfoList":[],"baseEnemyGroupList":[{"mApartIndex":0,"mStartIndex":0,"mEnemyInfo":{"type":0,"shape":1},"mCount":3,"mHp":0.0,"mEnemyAttribute":{"HpRate":1.0,"AttackRate":1.0,"MoveSpeedRate":1.0,"Defence":0.0,"ParamDict":{}}},{"mApartIndex":1,"mStartIndex":0,"mEnemyInfo":{"type":11,"shape":3},"mCount":2,"mHp":0.0,"mEnemyAttribute":{"HpRate":1.0,"AttackRate":1.0,"MoveSpeedRate":1.0,"Defence":0.0,"ParamDict":{}}},{"mApartIndex":1,"mStartIndex":2,"mEnemyInfo":{"type":11,"shape":1},"mCount":4,"mHp":0.0,"mEnemyAttribute":{"HpRate":1.0,"AttackRate":1.0,"MoveSpeedRate":1.0,"Defence":0.0,"ParamDict":{}}}],"interval":2,"endTime":592,"roundMode":0,"isShowBigWaveRound":false,"isBossRound":false,"isSkipWhenBossDie":false,"bossList":null,"musicRefenceName":null,"ParamArrayDict":{}}],"baseEnemyGroupList":[],"interval":0,"endTime":0,"roundMode":1,"isShowBigWaveRound":false,"isBossRound":false,"isSkipWhenBossDie":false,"bossList":null,"musicRefenceName":null,"ParamArrayDict":{}},{"name":"第3轮","info":"","roundInfoList":[{"name":"第1轮","info":"","roundInfoList":[],"baseEnemyGroupList":[{"mApartIndex":0,"mStartIndex":0,"mEnemyInfo":{"type":2,"shape":0},"mCount":3,"mHp":0.0,"mEnemyAttribute":{"HpRate":1.0,"AttackRate":1.0,"MoveSpeedRate":1.0,"Defence":0.0,"ParamDict":{}}},{"mApartIndex":1,"mStartIndex":0,"mEnemyInfo":{"type":11,"shape":1},"mCount":4,"mHp":0.0,"mEnemyAttribute":{"HpRate":1.0,"AttackRate":1.0,"MoveSpeedRate":1.0,"Defence":0.0,"ParamDict":{}}},{"mApartIndex":1,"mStartIndex":0,"mEnemyInfo":{"type":6,"shape":0},"mCount":3,"mHp":0.0,"mEnemyAttribute":{"HpRate":1.0,"AttackRate":1.0,"MoveSpeedRate":1.0,"Defence":0.0,"ParamDict":{}}}],"interval":2,"endTime":114,"roundMode":0,"isShowBigWaveRound":false,"isBossRound":false,"isSkipWhenBossDie":false,"bossList":null,"musicRefenceName":null,"ParamArrayDict":{}},{"name":"第2轮","info":"","roundInfoList":[],"baseEnemyGroupList":[{"mApartIndex":0,"mStartIndex":0,"mEnemyInfo":{"type":0,"shape":1},"mCount":3,"mHp":0.0,"mEnemyAttribute":null},{"mApartIndex":1,"mStartIndex":0,"mEnemyInfo":{"type":11,"shape":3},"mCount":4,"mHp":0.0,"mEnemyAttribute":null}],"interval":2,"endTime":596,"roundMode":0,"isShowBigWaveRound":false,"isBossRound":false,"isSkipWhenBossDie":false,"bossList":null,"musicRefenceName":null,"ParamArrayDict":{}}],"baseEnemyGroupList":[],"interval":0,"endTime":0,"roundMode":1,"isShowBigWaveRound":false,"isBossRound":false,"isSkipWhenBossDie":false,"bossList":null,"musicRefenceName":null,"ParamArrayDict":{}},{"name":"第4轮","info":"","roundInfoList":[{"name":"第1轮","info":"","roundInfoList":[],"baseEnemyGroupList":[{"mApartIndex":0,"mStartIndex":0,"mEnemyInfo":{"type":0,"shape":1},"mCount":3,"mHp":0.0,"mEnemyAttribute":{"HpRate":1.0,"AttackRate":1.0,"MoveSpeedRate":1.0,"Defence":0.0,"ParamDict":{}}},{"mApartIndex":1,"mStartIndex":0,"mEnemyInfo":{"type":11,"shape":3},"mCount":4,"mHp":0.0,"mEnemyAttribute":{"HpRate":1.0,"AttackRate":1.0,"MoveSpeedRate":1.0,"Defence":0.0,"ParamDict":{}}},{"mApartIndex":1,"mStartIndex":0,"mEnemyInfo":{"type":14,"shape":0},"mCount":2,"mHp":0.0,"mEnemyAttribute":{"HpRate":1.0,"AttackRate":1.0,"MoveSpeedRate":1.0,"Defence":0.0,"ParamDict":{}}}],"interval":2,"endTime":114,"roundMode":0,"isShowBigWaveRound":false,"isBossRound":false,"isSkipWhenBossDie":false,"bossList":null,"musicRefenceName":null,"ParamArrayDict":{}},{"name":"第2轮","info":"","roundInfoList":[],"baseEnemyGroupList":[{"mApartIndex":0,"mStartIndex":0,"mEnemyInfo":{"type":0,"shape":9},"mCount":1,"mHp":0.0,"mEnemyAttribute":{"HpRate":1.0,"AttackRate":1.0,"MoveSpeedRate":1.0,"Defence":0.0,"ParamDict":{}}},{"mApartIndex":1,"mStartIndex":2,"mEnemyInfo":{"type":11,"shape":1},"mCount":4,"mHp":0.0,"mEnemyAttribute":{"HpRate":1.0,"AttackRate":1.0,"MoveSpeedRate":1.0,"Defence":0.0,"ParamDict":{}}},{"mApartIndex":0,"mStartIndex":2,"mEnemyInfo":{"type":11,"shape":2},"mCount":2,"mHp":0.0,"mEnemyAttribute":{"HpRate":1.0,"AttackRate":1.0,"MoveSpeedRate":1.0,"Defence":0.0,"ParamDict":{}}}],"interval":2,"endTime":594,"roundMode":0,"isShowBigWaveRound":false,"isBossRound":false,"isSkipWhenBossDie":false,"bossList":null,"musicRefenceName":null,"ParamArrayDict":{}}],"baseEnemyGroupList":[],"interval":0,"endTime":0,"roundMode":1,"isShowBigWaveRound":false,"isBossRound":false,"isSkipWhenBossDie":false,"bossList":null,"musicRefenceName":null,"ParamArrayDict":{}},{"name":"第5轮","info":"","roundInfoList":[{"name":"第1轮","info":"","roundInfoList":[],"baseEnemyGroupList":[{"mApartIndex":1,"mStartIndex":0,"mEnemyInfo":{"type":11,"shape":1},"mCount":4,"mHp":0.0,"mEnemyAttribute":{"HpRate":1.0,"AttackRate":1.0,"MoveSpeedRate":1.0,"Defence":0.0,"ParamDict":{}}},{"mApartIndex":2,"mStartIndex":0,"mEnemyInfo":{"type":6,"shape":0},"mCount":3,"mHp":0.0,"mEnemyAttribute":{"HpRate":1.0,"AttackRate":1.0,"MoveSpeedRate":1.0,"Defence":0.0,"ParamDict":{}}},{"mApartIndex":1,"mStartIndex":0,"mEnemyInfo":{"type":14,"shape":0},"mCount":4,"mHp":0.0,"mEnemyAttribute":{"HpRate":1.0,"AttackRate":1.0,"MoveSpeedRate":1.0,"Defence":0.0,"ParamDict":{}}}],"interval":2,"endTime":114,"roundMode":0,"isShowBigWaveRound":false,"isBossRound":false,"isSkipWhenBossDie":false,"bossList":null,"musicRefenceName":null,"ParamArrayDict":{}},{"name":"第2轮","info":"","roundInfoList":[],"baseEnemyGroupList":[{"mApartIndex":0,"mStartIndex":0,"mEnemyInfo":{"type":0,"shape":2},"mCount":2,"mHp":0.0,"mEnemyAttribute":{"HpRate":1.0,"AttackRate":1.0,"MoveSpeedRate":1.0,"Defence":0.0,"ParamDict":{}}},{"mApartIndex":0,"mStartIndex":0,"mEnemyInfo":{"type":0,"shape":1},"mCount":3,"mHp":0.0,"mEnemyAttribute":{"HpRate":1.0,"AttackRate":1.0,"MoveSpeedRate":1.0,"Defence":0.0,"ParamDict":{}}}],"interval":2,"endTime":596,"roundMode":0,"isShowBigWaveRound":false,"isBossRound":false,"isSkipWhenBossDie":false,"bossList":null,"musicRefenceName":null,"ParamArrayDict":{}}],"baseEnemyGroupList":[],"interval":0,"endTime":0,"roundMode":1,"isShowBigWaveRound":false,"isBossRound":false,"isSkipWhenBossDie":false,"bossList":null,"musicRefenceName":null,"ParamArrayDict":{}},{"name":"第6轮","info":"","roundInfoList":[{"name":"第1轮","info":"","roundInfoList":[],"baseEnemyGroupList":[{"mApartIndex":0,"mStartIndex":0,"mEnemyInfo":{"type":2,"shape":0},"mCount":3,"mHp":0.0,"mEnemyAttribute":{"HpRate":1.0,"AttackRate":1.0,"MoveSpeedRate":1.0,"Defence":0.0,"ParamDict":{}}},{"mApartIndex":1,"mStartIndex":0,"mEnemyInfo":{"type":11,"shape":3},"mCount":4,"mHp":0.0,"mEnemyAttribute":{"HpRate":1.0,"AttackRate":1.0,"MoveSpeedRate":1.0,"Defence":0.0,"ParamDict":{}}},{"mApartIndex":1,"mStartIndex":0,"mEnemyInfo":{"type":14,"shape":0},"mCount":4,"mHp":0.0,"mEnemyAttribute":{"HpRate":1.0,"AttackRate":1.0,"MoveSpeedRate":1.0,"Defence":0.0,"ParamDict":{}}},{"mApartIndex":2,"mStartIndex":4,"mEnemyInfo":{"type":1,"shape":0},"mCount":4,"mHp":0.0,"mEnemyAttribute":{"HpRate":1.0,"AttackRate":1.0,"MoveSpeedRate":1.0,"Defence":0.0,"ParamDict":{}}}],"interval":2,"endTime":112,"roundMode":0,"isShowBigWaveRound":false,"isBossRound":false,"isSkipWhenBossDie":false,"bossList":null,"musicRefenceName":null,"ParamArrayDict":{}},{"name":"第2轮","info":"","roundInfoList":[],"baseEnemyGroupList":[{"mApartIndex":1,"mStartIndex":2,"mEnemyInfo":{"type":11,"shape":1},"mCount":4,"mHp":0.0,"mEnemyAttribute":{"HpRate":1.0,"AttackRate":1.0,"MoveSpeedRate":1.0,"Defence":0.0,"ParamDict":{}}},{"mApartIndex":0,"mStartIndex":2,"mEnemyInfo":{"type":0,"shape":3},"mCount":2,"mHp":0.0,"mEnemyAttribute":{"HpRate":1.0,"AttackRate":1.0,"MoveSpeedRate":1.0,"Defence":0.0,"ParamDict":{}}}],"interval":2,"endTime":596,"roundMode":0,"isShowBigWaveRound":false,"isBossRound":false,"isSkipWhenBossDie":false,"bossList":null,"musicRefenceName":null,"ParamArrayDict":{}}],"baseEnemyGroupList":[],"interval":0,"endTime":0,"roundMode":1,"isShowBigWaveRound":false,"isBossRound":false,"isSkipWhenBossDie":false,"bossList":null,"musicRefenceName":null,"ParamArrayDict":{}},{"name":"第7轮","info":"","roundInfoList":[{"name":"第1轮","info":"","roundInfoList":[],"baseEnemyGroupList":[{"mApartIndex":0,"mStartIndex":0,"mEnemyInfo":{"type":0,"shape":4},"mCount":2,"mHp":0.0,"mEnemyAttribute":{"HpRate":1.0,"AttackRate":1.0,"MoveSpeedRate":1.0,"Defence":0.0,"ParamDict":{}}},{"mApartIndex":1,"mStartIndex":0,"mEnemyInfo":{"type":11,"shape":1},"mCount":4,"mHp":0.0,"mEnemyAttribute":{"HpRate":1.0,"AttackRate":1.0,"MoveSpeedRate":1.0,"Defence":0.0,"ParamDict":{}}},{"mApartIndex":1,"mStartIndex":0,"mEnemyInfo":{"type":14,"shape":0},"mCount":4,"mHp":0.0,"mEnemyAttribute":{"HpRate":1.0,"AttackRate":1.0,"MoveSpeedRate":1.0,"Defence":0.0,"ParamDict":{}}}],"interval":2,"endTime":112,"roundMode":0,"isShowBigWaveRound":false,"isBossRound":false,"isSkipWhenBossDie":false,"bossList":null,"musicRefenceName":null,"ParamArrayDict":{}},{"name":"第2轮","info":"","roundInfoList":[],"baseEnemyGroupList":[{"mApartIndex":0,"mStartIndex":0,"mEnemyInfo":{"type":0,"shape":1},"mCount":3,"mHp":0.0,"mEnemyAttribute":{"HpRate":1.0,"AttackRate":1.0,"MoveSpeedRate":1.0,"Defence":0.0,"ParamDict":{}}},{"mApartIndex":2,"mStartIndex":0,"mEnemyInfo":{"type":2,"shape":0},"mCount":5,"mHp":0.0,"mEnemyAttribute":{"HpRate":1.0,"AttackRate":1.0,"MoveSpeedRate":1.0,"Defence":0.0,"ParamDict":{}}}],"interval":2,"endTime":594,"roundMode":0,"isShowBigWaveRound":false,"isBossRound":false,"isSkipWhenBossDie":false,"bossList":null,"musicRefenceName":null,"ParamArrayDict":{}}],"baseEnemyGroupList":[],"interval":0,"endTime":0,"roundMode":1,"isShowBigWaveRound":false,"isBossRound":false,"isSkipWhenBossDie":false,"bossList":null,"musicRefenceName":null,"ParamArrayDict":{}},{"name":"第8轮","info":"","roundInfoList":[{"name":"第1轮","info":"","roundInfoList":[],"baseEnemyGroupList":[{"mApartIndex":0,"mStartIndex":0,"mEnemyInfo":{"type":19,"shape":0},"mCount":3,"mHp":0.0,"mEnemyAttribute":{"HpRate":1.0,"AttackRate":1.0,"MoveSpeedRate":1.0,"Defence":0.0,"ParamDict":{}}},{"mApartIndex":1,"mStartIndex":0,"mEnemyInfo":{"type":19,"shape":0},"mCount":3,"mHp":0.0,"mEnemyAttribute":{"HpRate":1.0,"AttackRate":1.0,"MoveSpeedRate":1.0,"Defence":0.0,"ParamDict":{}}}],"interval":0,"endTime":120,"roundMode":0,"isShowBigWaveRound":false,"isBossRound":false,"isSkipWhenBossDie":false,"bossList":null,"musicRefenceName":null,"ParamArrayDict":{}},{"name":"第2轮","info":"","roundInfoList":[],"baseEnemyGroupList":[{"mApartIndex":0,"mStartIndex":2,"mEnemyInfo":{"type":0,"shape":1},"mCount":3,"mHp":0.0,"mEnemyAttribute":{"HpRate":1.0,"AttackRate":1.0,"MoveSpeedRate":1.0,"Defence":0.0,"ParamDict":{}}},{"mApartIndex":1,"mStartIndex":0,"mEnemyInfo":{"type":14,"shape":0},"mCount":4,"mHp":0.0,"mEnemyAttribute":{"HpRate":1.0,"AttackRate":1.0,"MoveSpeedRate":1.0,"Defence":0.0,"ParamDict":{}}},{"mApartIndex":1,"mStartIndex":2,"mEnemyInfo":{"type":11,"shape":1},"mCount":4,"mHp":0.0,"mEnemyAttribute":{"HpRate":1.0,"AttackRate":1.0,"MoveSpeedRate":1.0,"Defence":0.0,"ParamDict":{}}}],"interval":2,"endTime":108,"roundMode":0,"isShowBigWaveRound":false,"isBossRound":false,"isSkipWhenBossDie":false,"bossList":null,"musicRefenceName":null,"ParamArrayDict":{}}],"baseEnemyGroupList":[],"interval":0,"endTime":0,"roundMode":1,"isShowBigWaveRound":true,"isBossRound":false,"isSkipWhenBossDie":false,"bossList":null,"musicRefenceName":null,"ParamArrayDict":{}}],"baseEnemyGroupList":[],"interval":0,"endTime":0,"roundMode":1,"isShowBigWaveRound":false,"isBossRound":false,"isSkipWhenBossDie":false,"bossList":null,"musicRefenceName":"MeiWeiNight1","ParamArrayDict":{}}],"defaultMode":0,"apartList":[[2,3,4],[0,1,5,6],[0,1,2,3,4,5,6]],"perpareTime":1080,"isEnableStartCard":true,"startCardInfoList":[[[{"type":9,"maxShape":0,"maxLevel":0}],[{"type":9,"maxShape":0,"maxLevel":0}],[],[],[],[{"type":9,"maxShape":0,"maxLevel":0}],[{"type":9,"maxShape":0,"maxLevel":0}]],[[{"type":9,"maxShape":0,"maxLevel":0}],[{"type":9,"maxShape":0,"maxLevel":0}],[],[],[],[{"type":9,"maxShape":0,"maxLevel":0}],[{"type":9,"maxShape":0,"maxLevel":0}]],[[],[],[],[],[],[],[]],[[],[],[],[],[],[],[]],[[],[],[],[],[],[],[]],[[],[],[],[],[],[],[]],[[],[],[],[],[],[],[]],[[],[],[],[],[],[],[]],[[],[],[],[],[],[],[]]],"startBGMRefence":"MeiWeiNight0","ParamArrayDict":{"isNoCat":[1.0]}}