{"name":"新建关卡1","background":null,"illustrate":null,"additionalNotes":null,"chapterIndex":2,"sceneIndex":2,"stageIndex":1,"startCost":0,"isEnableTimeLimit":false,"totalSeconds":0,"isEnableCardLimit":false,"availableCardInfoList":[],"isEnableCardCount":false,"cardCount":0,"roundInfoList":[{"name":"第1轮","info":"","roundInfoList":[],"baseEnemyGroupList":[{"mApartIndex":0,"mStartIndex":4,"mEnemyInfo":{"type":1,"shape":0},"mCount":5,"mHp":0.0}],"interval":0,"endTime":0,"roundMode":0,"isBossRound":false,"bossList":null}],"waveIndexList":[],"defaultMode":0,"apartList":[[1,2,3,4,5]],"perpareTime":0}